zenlogger/__init__.py
zenlogger/main.py
zenlogger-0.0.4.dist-info/LICENSE
zenlogger-0.0.4.dist-info/METADATA
zenlogger-0.0.4.dist-info/WHEEL
zenlogger-0.0.4.dist-info/RECORD
